larkpy/__init__.py
larkpy/_typing.py
larkpy/api.py
larkpy/bitTable.py
larkpy/calendar.py
larkpy/card.py
larkpy/docx.py
larkpy/im.py
larkpy/log.py
larkpy/webhook.py
larkpy-0.3.0.dist-info/licenses/LICENSE
larkpy-0.3.0.dist-info/METADATA
larkpy-0.3.0.dist-info/WHEEL
larkpy-0.3.0.dist-info/top_level.txt
larkpy-0.3.0.dist-info/RECORD
