Metadata-Version: 2.4
Name: larkpy
Version: 0.3.0
Summary: 飞书开放平台 Python 接口 | Python SDK for Lark
Author-email: Benature Wang <benature246@gmail.com>
License: MIT
Project-URL: Homepage, https://github.com/Benature/larkpy
Project-URL: Repository, https://github.com/Benature/larkpy
Classifier: Programming Language :: Python :: 3.7
Classifier: License :: OSI Approved :: MIT License
Classifier: Operating System :: OS Independent
Requires-Python: >=3.7
License-File: LICENSE
Requires-Dist: requests
Requires-Dist: bs4
Requires-Dist: lxml
Requires-Dist: pandas
Requires-Dist: requests_toolbelt
Dynamic: license-file
